README
setup.py
bm_structures.egg-info/PKG-INFO
bm_structures.egg-info/SOURCES.txt
bm_structures.egg-info/dependency_links.txt
bm_structures.egg-info/not-zip-safe
bm_structures.egg-info/top_level.txt
src/__init__.py
src/bloom.py
src/fsm.py
src/graph.py
src/linked_list.py
src/nd_fsm.py
src/proxy.py
src/queue.py
src/stack.py
src/trampoline.py