Metadata-Version: 1.0
Name: bm-structures
Version: 0.0.1.6
Summary: Common structures for python
Home-page: UNKNOWN
Author: Alex Toney
Author-email: toneyalex@gmail.com
License: GPL
Platform: UNKNOWN
